kmtronic_usb_relay/__init__.py
kmtronic_usb_relay/com_utils.py
kmtronic_usb_relay/four_channel_relay.py
kmtronic_usb_relay/four_channel_relay_app.py
kmtronic_usb_relay/four_channel_relay_gui.py
kmtronic_usb_relay-26.0.0.dist-info/WHEEL
kmtronic_usb_relay-26.0.0.dist-info/METADATA
kmtronic_usb_relay-26.0.0.dist-info/RECORD
