Metadata-Version: 2.3
Name: kmtronic-usb-relay
Version: 26.0.0
Summary: Python library for KMTronic USB Relay
Keywords: python,KMTronic,USB,relay,app
Author: chaitu-ycr
Author-email: chaitu-ycr <chaitu.ycr@gmail.com>
License: MIT License
Classifier: Programming Language :: Python :: 3
Classifier: License :: OSI Approved :: MIT License
Classifier: Operating System :: Microsoft :: Windows
Requires-Dist: pyserial
Requires-Dist: customtkinter
Requires-Dist: fastapi[all]
Requires-Dist: nicegui[native]
Requires-Python: >=3.10, <=3.14
Project-URL: homepage, https://github.com/chaitu-ycr/kmtronic-usb-relay
Project-URL: repository, https://github.com/chaitu-ycr/kmtronic-usb-relay
Project-URL: documentation, https://chaitu-ycr.github.io/kmtronic-usb-relay
